<?xml version="1.0" encoding="UTF-8"?>
<ORDERCHANGE xmlns="http://www.opentrans.org/XMLSchema/2.1" xmlns:xsi="http://www.w3.org/2001/XMLSchema-instance" xmlns:bmecat="http://www.bmecat.org/bmecat/2005" xmlns:xmime="http://www.w3.org/2005/05/xmlmime" xsi:schemaLocation="http://www.opentrans.org/XMLSchema/2.1 https://merchantcenter.check24.de/sdk/opentrans/schema-definitions/opentrans_2_1.xsd http://www.bmecat.org/bmecat/2005 https://merchantcenter.check24.de/sdk/opentrans/schema-definitions/bmecat_2005.xsd http://www.w3.org/2005/05/xmlmime https://merchantcenter.check24.de/sdk/opentrans/schema-definitions/xmlmime.xsd http://www.w3.org/2000/09/xmldsig# https://merchantcenter.check24.de/sdk/opentrans/schema-definitions/xmldsig-core-schema.xsd" version="2.1">
  <ORDERCHANGE_HEADER>
    <ORDERCHANGE_INFO>
      <ORDER_ID>MQQTPS</ORDER_ID>
      <ORDERCHANGE_DATE>2022-05-03T00:24:15</ORDERCHANGE_DATE>
      <ORDER_DATE>2021-10-28T16:58:03</ORDER_DATE>
      <ORDERCHANGE_SEQUENCE_ID>1</ORDERCHANGE_SEQUENCE_ID>
      <PARTIES>
        <PARTY>
          <bmecat:PARTY_ID type="check24">delivery</bmecat:PARTY_ID>
          <PARTY_ROLE>delivery</PARTY_ROLE>
          <ADDRESS>
            <bmecat:NAME2>Christian B3</bmecat:NAME2>
            <bmecat:NAME3>Hecker B3</bmecat:NAME3>
            <bmecat:STREET>Mendelstraße 83</bmecat:STREET>
            <bmecat:ZIP>48149</bmecat:ZIP>
            <bmecat:CITY>Münster</bmecat:CITY>
            <bmecat:COUNTRY>Deutschland</bmecat:COUNTRY>
            <bmecat:COUNTRY_CODED>DE</bmecat:COUNTRY_CODED>
            <bmecat:PHONE>+49251111111234</bmecat:PHONE>
            <bmecat:EMAIL>c-ehfdhahamaeagukgmikaed-eguiigafge@ch24.de</bmecat:EMAIL>
          </ADDRESS>
        </PARTY>
        <PARTY>
          <bmecat:PARTY_ID type="check24">invoice_issuer</bmecat:PARTY_ID>
          <PARTY_ROLE>invoice_issuer</PARTY_ROLE>
          <ADDRESS>
            <bmecat:NAME>CHECK24 Vergleichsportal Shopping GmbH</bmecat:NAME>
            <bmecat:NAME2>Shopping</bmecat:NAME2>
            <bmecat:NAME3>CHECK24 (nur Rechnungsadresse)</bmecat:NAME3>
            <bmecat:STREET>Erika-Mann-Str. 55</bmecat:STREET>
            <bmecat:ZIP>80636</bmecat:ZIP>
            <bmecat:CITY>München</bmecat:CITY>
            <bmecat:COUNTRY>Deutschland</bmecat:COUNTRY>
            <bmecat:COUNTRY_CODED>DE</bmecat:COUNTRY_CODED>
            <bmecat:PHONE>+49251111111234</bmecat:PHONE>
            <bmecat:EMAIL>c-ehfdhahamaeagukgmikaed-eguiigafge@ch24.de</bmecat:EMAIL>
          </ADDRESS>
        </PARTY>
        <PARTY>
          <bmecat:PARTY_ID type="check24">supplier</bmecat:PARTY_ID>
          <PARTY_ROLE>supplier</PARTY_ROLE>
          <ADDRESS>
            <bmecat:NAME>OXID Testshop OpenTrans 2.1</bmecat:NAME>
            <bmecat:STREET>Wallstraße 9-13</bmecat:STREET>
            <bmecat:ZIP>10179</bmecat:ZIP>
            <bmecat:CITY>Berlin</bmecat:CITY>
            <bmecat:COUNTRY_CODED>DE</bmecat:COUNTRY_CODED>
          </ADDRESS>
        </PARTY>
      </PARTIES>
      <ORDER_PARTIES_REFERENCE>
        <bmecat:BUYER_IDREF type="check24">delivery</bmecat:BUYER_IDREF>
        <bmecat:SUPPLIER_IDREF type="check24">supplier</bmecat:SUPPLIER_IDREF>
        <SHIPMENT_PARTIES_REFERENCE>
          <DELIVERY_IDREF type="check24">delivery</DELIVERY_IDREF>
        </SHIPMENT_PARTIES_REFERENCE>
      </ORDER_PARTIES_REFERENCE>
      <REMARKS type="action">returnrequest</REMARKS>
      <REMARKS type="versionorderapi">2.0</REMARKS>
    </ORDERCHANGE_INFO>
  </ORDERCHANGE_HEADER>
  <ORDERCHANGE_ITEM_LIST>
    <ORDER_ITEM>
      <LINE_ITEM_ID>O+60rDV3jBvbefmjlU7ePA==</LINE_ITEM_ID>
      <PRODUCT_ID>
        <bmecat:SUPPLIER_PID>DEF3</bmecat:SUPPLIER_PID>
        <bmecat:DESCRIPTION_SHORT>Testprodukt: NICHT BESTELLEN: Drei Haufen Pappe für Moebel</bmecat:DESCRIPTION_SHORT>
      </PRODUCT_ID>
      <QUANTITY>-1</QUANTITY>
      <bmecat:ORDER_UNIT>C62</bmecat:ORDER_UNIT>
      <PRICE_LINE_AMOUNT>14.99</PRICE_LINE_AMOUNT>
      <CUSTOMER_ORDER_REFERENCE>
        <ORDER_ID>MQQTPS</ORDER_ID>
        <LINE_ITEM_ID>O+60rDV3jBvbefmjlU7ePA==</LINE_ITEM_ID>
      </CUSTOMER_ORDER_REFERENCE>
      <SHIPMENT_PARTIES_REFERENCE>
        <DELIVERY_IDREF type="check24">delivery</DELIVERY_IDREF>
      </SHIPMENT_PARTIES_REFERENCE>
      <REMARKS type="reasonkey">order_cancelled_in_shop</REMARKS>
      <REMARKS type="reasondescription">Order cancelled in Oxid shop</REMARKS>
    </ORDER_ITEM>
  </ORDERCHANGE_ITEM_LIST>
  <ORDERCHANGE_SUMMARY>
    <TOTAL_ITEM_NUM>1</TOTAL_ITEM_NUM>
    <TOTAL_AMOUNT>14.99</TOTAL_AMOUNT>
  </ORDERCHANGE_SUMMARY>
</ORDERCHANGE>
